image_processing_mod/__init__.py
image_processing_mod/processing/__init__.py
image_processing_mod/processing/combination.py
image_processing_mod/processing/transformation.py
image_processing_mod/utils/__init__.py
image_processing_mod/utils/io.py
image_processing_mod/utils/plot.py
image_processing_mod-0.0.1.dist-info/METADATA
image_processing_mod-0.0.1.dist-info/WHEEL
image_processing_mod-0.0.1.dist-info/top_level.txt
image_processing_mod-0.0.1.dist-info/RECORD
