Metadata-Version: 2.1
Name: image_processing_mod
Version: 0.0.1
Summary: Image Processing Package using Skimage
Home-page: https://github.com/Marcoswryell/image-processing-package.git
Author: Marcos
Requires-Python: >=3.8
Requires-Dist: matplotlib
Requires-Dist: numpy
Requires-Dist: scikit-image (>=0.16.1)
